canvas_cli/__init__.py
canvas_cli/__version__.py
canvas_cli/api.py
canvas_cli/args.py
canvas_cli/cli.py
canvas_cli/cli_utils.py
canvas_cli/command_clone.py
canvas_cli/command_status.py
canvas_cli/config.py
canvas_cli/tui.py
canvas_cli/tui_utils.py
canvas_cmd-0.2.0.dist-info/licenses/COPYING
canvas_cmd-0.2.0.dist-info/METADATA
canvas_cmd-0.2.0.dist-info/WHEEL
canvas_cmd-0.2.0.dist-info/entry_points.txt
canvas_cmd-0.2.0.dist-info/top_level.txt
canvas_cmd-0.2.0.dist-info/RECORD
