Metadata-Version: 2.4
Name: canvas-cmd
Version: 0.2.0
Summary: A command-line tool for interacting with Canvas LMS
Home-page: https://github.com/PhantomOffKanagawa/canvas-cli
Author: PhantomOffKanagawa
Author-email: harry@surmafamily.com
Project-URL: Bug Tracker, https://github.com/PhantomOffKanagawa/canvas-cli/issues
Project-URL: Documentation, https://github.com/PhantomOffKanagawa/canvas-cli/wiki
Project-URL: Source Code, https://github.com/PhantomOffKanagawa/canvas-cli
Classifier: Development Status :: 4 - Beta
Classifier: Programming Language :: Python :: 3
Classifier: Programming Language :: Python :: 3.9
Classifier: Programming Language :: Python :: 3.10
Classifier: License :: OSI Approved :: GNU General Public License v3 (GPLv3)
Classifier: Operating System :: OS Independent
Classifier: Environment :: Console
Classifier: Intended Audience :: Education
Classifier: Topic :: Education
Classifier: Topic :: Utilities
Requires-Python: >=3.9
License-File: COPYING
Requires-Dist: requests>=2.25.0
Provides-Extra: gui
Requires-Dist: rich; extra == "gui"
Provides-Extra: convert
Requires-Dist: markitdown[docx,pdf]>=0.1.0; extra == "convert"
Provides-Extra: full
Requires-Dist: rich; extra == "full"
Requires-Dist: markitdown[docx,pdf]>=0.1.0; extra == "full"
Provides-Extra: windows
Requires-Dist: windows-curses; extra == "windows"
Dynamic: author
Dynamic: author-email
Dynamic: classifier
Dynamic: description
Dynamic: description-content-type
Dynamic: home-page
Dynamic: license-file
Dynamic: project-url
Dynamic: provides-extra
Dynamic: requires-dist
Dynamic: requires-python
Dynamic: summary
